kmeanstf/__init__.py
kmeanstf/__version__.py
kmeanstf/_initializer.py
kmeanstf/kmeanstf.py
kmeanstf-0.8.1.dist-info/LICENSE
kmeanstf-0.8.1.dist-info/METADATA
kmeanstf-0.8.1.dist-info/WHEEL
kmeanstf-0.8.1.dist-info/top_level.txt
kmeanstf-0.8.1.dist-info/RECORD
