Metadata-Version: 2.1
Name: kmeanstf
Version: 0.8.1
Summary: TensorFlow-based implementation of k-means, k-means++ and tunnel k-means. GPU-enabled.
Home-page: https://github.com/gittar/kmeanstf
Author: Bernd Fritzke
Author-email: fritzke@web.de
License: BSD 3-Clause License
Platform: UNKNOWN
Classifier: License :: OSI Approved :: BSD License
Classifier: Programming Language :: Python
Classifier: Programming Language :: Python :: 3
Classifier: Programming Language :: Python :: 3.6
Classifier: Programming Language :: Python :: Implementation :: CPython
Classifier: Programming Language :: Python :: Implementation :: PyPy
Classifier: Topic :: Scientific/Engineering :: Artificial Intelligence
Classifier: Topic :: Scientific/Engineering :: Information Analysis
Requires-Python: >=3.6.0
Requires-Dist: numpy
Requires-Dist: matplotlib
Requires-Dist: scikit-learn
Requires-Dist: tensorflow (>=1.15.0)
Requires-Dist: nvidia-ml-py3
